verta/__init__.py
verta/__main__.py
verta/verta_clustering.py
verta/verta_commands.py
verta/verta_config.py
verta/verta_consistency.py
verta/verta_data_loader.py
verta/verta_decisions.py
verta/verta_gaze.py
verta/verta_geometry.py
verta/verta_gui.py
verta/verta_intent_recognition.py
verta/verta_logging.py
verta/verta_metrics.py
verta/verta_plotting.py
verta/verta_prediction.py
verta/verta_progress.py
verta/verta_validation.py
verta-1.0.5.dist-info/licenses/LICENSE
verta-1.0.5.dist-info/METADATA
verta-1.0.5.dist-info/WHEEL
verta-1.0.5.dist-info/entry_points.txt
verta-1.0.5.dist-info/top_level.txt
verta-1.0.5.dist-info/RECORD
