Metadata-Version: 2.4
Name: verta
Version: 1.0.5
Summary: VERTA - Virtual Environment Route and Trajectory Analyzer: A Python tool for route and trajectory analysis in virtual environments
Author-email: Niklas Suhre <suhre@verkehr.tu-darmstadt.de>
License-Expression: MIT
Project-URL: Homepage, https://github.com/ruedi99ms/VERTA
Project-URL: Documentation, https://github.com/ruedi99ms/VERTA#readme
Project-URL: Repository, https://github.com/ruedi99ms/VERTA
Project-URL: Issues, https://github.com/ruedi99ms/VERTA/issues
Keywords: trajectory-analysis,route-analysis,virtual-reality,vr,behavioral-analysis,machine-learning,intent-recognition,gaze-tracking,spatial-analysis
Classifier: Development Status :: 4 - Beta
Classifier: Intended Audience :: Science/Research
Classifier: Intended Audience :: Developers
Classifier: Programming Language :: Python :: 3
Classifier: Programming Language :: Python :: 3.8
Classifier: Programming Language :: Python :: 3.9
Classifier: Programming Language :: Python :: 3.10
Classifier: Programming Language :: Python :: 3.11
Classifier: Programming Language :: Python :: 3.12
Classifier: Topic :: Scientific/Engineering
Classifier: Topic :: Scientific/Engineering :: Visualization
Classifier: Topic :: Software Development :: Libraries :: Python Modules
Requires-Python: >=3.8
License-File: LICENSE
Requires-Dist: numpy>=1.20.0
Requires-Dist: pandas>=1.3.0
Requires-Dist: matplotlib>=3.3.0
Requires-Dist: scikit-learn>=1.0.0
Requires-Dist: tqdm>=4.60.0
Requires-Dist: seaborn>=0.12.0
Provides-Extra: yaml
Requires-Dist: pyyaml; extra == "yaml"
Provides-Extra: parquet
Requires-Dist: pyarrow; extra == "parquet"
Provides-Extra: gui
Requires-Dist: streamlit>=1.28.0; extra == "gui"
Requires-Dist: plotly>=5.15.0; extra == "gui"
Provides-Extra: test
Requires-Dist: pytest>=7.0.0; extra == "test"
Dynamic: license-file
